rest_framework_push_notifications-0.1.0.dist-info/top_level.txt
rest_framework_push_notifications-0.1.0.dist-info/DESCRIPTION.rst
rest_framework_push_notifications-0.1.0.dist-info/RECORD
rest_framework_push_notifications-0.1.0.dist-info/metadata.json
rest_framework_push_notifications-0.1.0.dist-info/METADATA
rest_framework_push_notifications-0.1.0.dist-info/WHEEL
rest_framework_push_notifications/__init__.py
rest_framework_push_notifications/serializers.py
rest_framework_push_notifications/views.py
rest_framework_push_notifications/urls.py
