Metadata-Version: 2.0
Name: rest-framework-push-notifications
Version: 0.1.0
Summary: Rest Framework Serializers and Views for Django push notifications.
Home-page: https://github.com/incuna/rest-framework-push-notifications
Author: Incuna
Author-email: admin@incuna.com
License: BSD
Platform: UNKNOWN
Requires-Dist: djangorestframework (>=3.1.0,<3.2)
Requires-Dist: django-push-notifications (>=1.2,<1.3)
